{"name":"employeeEndToEndTestApi","id":"com.mycompany.tests.API_Get_Delete_Tests:employeeEndToEndTestApi","testCaseName":"com.mycompany.tests.API_Get_Delete_Tests","testSteps":[{"number":1,"description":"Get employee details","duration":5065,"startTime":"2021-04-16T13:59:13.993-05:00[America/Chicago]","result":"SUCCESS","precondition":false,"level":0},{"number":2,"description":"Verify Status Code","duration":155,"startTime":"2021-04-16T13:59:19.063-05:00[America/Chicago]","exception":{"errorType":"java.lang.AssertionError","message":"1 expectation failed.\nExpected status code \u003c200\u003e but was \u003c429\u003e.\n","stackTrace":[{"declaringClass":"io.restassured.internal.ResponseSpecificationImpl","methodName":"validateResponseIfRequired","fileName":"ResponseSpecificationImpl.groovy","lineNumber":656},{"declaringClass":"io.restassured.internal.ResponseSpecificationImpl","methodName":"statusCode","fileName":"ResponseSpecificationImpl.groovy","lineNumber":125},{"declaringClass":"io.restassured.internal.ResponseSpecificationImpl","methodName":"statusCode","fileName":"ResponseSpecificationImpl.groovy","lineNumber":133},{"declaringClass":"io.restassured.internal.ValidatableResponseOptionsImpl","methodName":"statusCode","fileName":"ValidatableResponseOptionsImpl.java","lineNumber":119},{"declaringClass":"com.mycompany.steps.ApiTestSteps","methodName":"verifyStatusCodeForSuccess","fileName":"ApiTestSteps.java","lineNumber":40},{"declaringClass":"com.mycompany.tests.API_Get_Delete_Tests","methodName":"employeeEndToEndTestApi","fileName":"API_Get_Delete_Tests.java","lineNumber":21}]},"result":"FAILURE","precondition":false,"level":0},{"number":3,"description":"Delete employee","duration":3,"startTime":"2021-04-16T13:59:19.222-05:00[America/Chicago]","result":"SKIPPED","precondition":false,"level":0}],"userStory":{"id":"com.mycompany.tests.API_Get_Delete_Tests","storyName":"API get delete tests","storyClassName":"com.mycompany.tests.API_Get_Delete_Tests","path":"com.mycompany.tests","type":"story"},"featureTag":{"name":"Tests/API get delete tests","type":"story","displayName":"Tests/API get delete tests"},"title":"Employee end to end test api","tags":[{"name":"Tests/API get delete tests","type":"story","displayName":"Tests/API get delete tests"}],"startTime":"2021-04-16T13:59:13.840-05:00[America/Chicago]","duration":5404,"testFailureCause":{"errorType":"java.lang.AssertionError","message":"1 expectation failed.\nExpected status code \u003c200\u003e but was \u003c429\u003e.\n","stackTrace":[{"declaringClass":"io.restassured.internal.ResponseSpecificationImpl","methodName":"validateResponseIfRequired","fileName":"ResponseSpecificationImpl.groovy","lineNumber":656},{"declaringClass":"io.restassured.internal.ResponseSpecificationImpl","methodName":"statusCode","fileName":"ResponseSpecificationImpl.groovy","lineNumber":125},{"declaringClass":"io.restassured.internal.ResponseSpecificationImpl","methodName":"statusCode","fileName":"ResponseSpecificationImpl.groovy","lineNumber":133},{"declaringClass":"io.restassured.internal.ValidatableResponseOptionsImpl","methodName":"statusCode","fileName":"ValidatableResponseOptionsImpl.java","lineNumber":119},{"declaringClass":"com.mycompany.steps.ApiTestSteps","methodName":"verifyStatusCodeForSuccess","fileName":"ApiTestSteps.java","lineNumber":40},{"declaringClass":"com.mycompany.tests.API_Get_Delete_Tests","methodName":"employeeEndToEndTestApi","fileName":"API_Get_Delete_Tests.java","lineNumber":21}]},"testFailureClassname":"java.lang.AssertionError","testFailureMessage":"1 expectation failed.\nExpected status code \u003c200\u003e but was \u003c429\u003e.\n","testFailureSummary":"FAILURE;java.lang.AssertionError;1 expectation failed.\nExpected status code \u003c200\u003e but was \u003c429\u003e.\n;ResponseSpecificationImpl.groovy","projectKey":"","annotatedResult":"FAILURE","manual":false,"testSource":"JUnit","result":"FAILURE"}